{
  "branch_name": "fn-5-architecture-patterns-skills",
  "completion_review_status": "ship",
  "completion_reviewed_at": "2026-02-12T17:58:48.929032Z",
  "created_at": "2026-02-11T22:23:12.096543Z",
  "default_impl": null,
  "default_review": null,
  "default_sync": null,
  "depends_on_epics": [
    "fn-2-plugin-skeleton-and-infrastructure"
  ],
  "id": "fn-5-architecture-patterns-skills",
  "next_task": 1,
  "plan_review_status": "ship",
  "plan_reviewed_at": "2026-02-12T05:35:37.031689Z",
  "spec_path": ".flow/specs/fn-5-architecture-patterns-skills.md",
  "status": "done",
  "title": "Architecture Patterns Skills",
  "updated_at": "2026-02-12T17:59:10.493552Z"
}
